{
    "num": 21,
    "element": "Neutral",
    "name": "Neo",
    "class": "Close-Range",
    "description": "Neo has weak Defense at low ranks, so raise its rank before bringing it to battle. It can Excite foes to prevent movement",
    "sprite": "images/sprites/Neo_Battle.png",
    "stats": {
        "LP": 440,
        "ATT": 70,
        "DEF": 36,
        "ACC": 50,
        "SPE": 14
    },
    "skills": [
        {
            "name": "Neo Bite",
            "baseDamage": 15,
            "fpCost": 50
        },
        {
            "name": "Neo Combo",
            "baseDamage": 36,
            "fpCost": 120,
            "effect": {
                "description": "Silver Excite",
                "rate": 30
            }
        },
        {
            "name": "Neo Fury",
            "baseDamage": 72,
            "fpCost": 240,
            "effect": {
                "description": "Silver Excite",
                "rate": 50
            }
        },
        {
            "name": "Law of the Jungle",
            "fpCost": 50,
            "effect": {
                "description": "Recover using ally LP"
            }
        },
        {
            "name": "Raging Storm",
            "fpCost": 340,
            "effect": {
                "description": "Gold Excite (team)",
                "rate": 70
            }
        }
    ],
    "support": {},
    "misc": {
        "genus": "Neovenator",
        "group": "Theropods",
        "era": "Mesozoic Cretaceous",
        "length": "26 ft. - 7.9 m. (Medium)",
        "diet": "Carnivore",
        "discovered": ["England"]
    }
}
